monkfreemobile/__init__.py
monkfreemobile/api/__init__.py
monkfreemobile/api/sms/__init__.py
monkfreemobile/api/sms/client.py
tests/__init__.py
monkfreemobile-1.1.0.dist-info/LICENSE.md
monkfreemobile-1.1.0.dist-info/METADATA
monkfreemobile-1.1.0.dist-info/WHEEL
monkfreemobile-1.1.0.dist-info/top_level.txt
monkfreemobile-1.1.0.dist-info/RECORD
